{
  "blocks": [
    {
      "items": [
        {
          "count": 1,
          "id": "3340"
        },
        {
          "count": 1,
          "id": "3341"
        },
        {
          "count": 1,
          "id": "3361"
        },
        {
          "count": 1,
          "id": "3364"
        }
      ],
      "recMath": false,
      "type": "Recommended Trinkets"
    },
    {
      "items": [
        {
          "count": 1,
          "id": "2041"
        },
        {
          "count": 1,
          "id": "2003"
        },
        {
          "count": 1,
          "id": "2043"
        },
        {
          "count": 1,
          "id": "2004"
        },
        {
          "count": 1,
          "id": "2044"
        }
      ],
      "recMath": false,
      "type": "Recommended Consumables"
    },
    {
      "items": [
        {
          "count": 1,
          "id": "1001"
        },
        {
          "count": 1,
          "id": "3020"
        },
        {
          "count": 1,
          "id": "3158"
        }
      ],
      "recMath": false,
      "type": "Recommended Boots"
    },
    {
      "items": [],
      "recMath": false,
      "type": "Recommended Jungle"
    },
    {
      "items": [
        {
          "count": 1,
          "id": "3100"
        },
        {
          "count": 1,
          "id": "3157"
        },
        {
          "count": 1,
          "id": "3165"
        },
        {
          "count": 1,
          "id": "3089"
        },
        {
          "count": 1,
          "id": "3078"
        },
        {
          "count": 1,
          "id": "3153"
        },
        {
          "count": 1,
          "id": "3135"
        }
      ],
      "recMath": false,
      "type": "Recommended Endgame"
    },
    {
      "items": [
        {
          "count": 1,
          "id": "2140"
        },
        {
          "count": 1,
          "id": "2139"
        }
      ],
      "recMath": false,
      "type": "Recommended Elixirs"
    }
  ],
  "map": "any",
  "mode": "any",
  "priority": true,
  "title": "Fizz",
  "type": "custom"
}