{
  "boots": [
    "Mercury's Treads",
    "Boots of Mobility",
    "Ninja Tabi",
    "Boots of Speed"
  ],
  "buildObj": {},
  "consumables": [
    "Health Potion",
    "Vision Ward",
    "Stealth Ward"
  ],
  "endgame": [
    "Thornmail",
    "Warmog's Armor",
    "Rylai's Crystal Scepter",
    "Randuin's Omen",
    "Liandry's Torment",
    "Dead Man's Plate",
    "Abyssal Scepter",
    "Sunfire Cape",
    "Spirit Visage"
  ],
  "trinkets": [
    "Oracle's Lens (Trinket)",
    "Warding Totem (Trinket)",
    "Sweeping Lens (Trinket)",
    "Greater Stealth Totem (Trinket)"
  ]
}
